{
  "64": ["eth0", "eth1", "eth2", "eth3", "eth3"],
  "archer-c7-v2": ["eth0.1", "eth1.2", "eth1.3", "eth1.4", "eth1.5"],
  "dir-860l-b1": ["eth0.1", "eth0.2", "eth0.3", "eth0.3", "eth0.5"],
  "erlite": ["eth0", "eth1", "eth2"],
  "ea3500": ["eth1", "eth0.3", "eth0.4", "eth0.5", "eth0.6"],
  "gl-ar750": ["eth0", "eth1.1", "eth1.2"],
  "gl-b1300": ["eth0.3", "eth0.4", "eth1"],
  "linksys-wrt3200acm": ["eth0.1", "eth0.3", "eth0.4", "eth0.5", "eth1.2"],
  "linksys_wrt3200acm": ["eth0.1", "eth0.3", "eth0.4", "eth0.5", "eth1.2"],
  "linksys-wrt32x": ["eth0.1", "eth0.3", "eth0.4", "eth0.5", "eth1.2"],
  "linksys_wrt32x": ["eth0.1", "eth0.3", "eth0.4", "eth0.5", "eth1.2"],
  "linksys_ea6350v3": ["eth0.11", "eth0.12", "eth0.13", "eth0.14", "eth1"],
  "mynet-n600": ["eth0.1", "eth0.2", "eth0.3", "eth0.4", "eth1"],
  "mynet-n750": ["eth0.1", "eth0.4", "eth0.5", "eth0.3", "eth0.2"],
  "friendlyarm_nanopi-r2s": ["eth1", "eth0"],
  "rpi-2": ["eth0"],
  "rpi-3": ["eth0"],
  "tl-wdr3600-v1": ["eth0.2", "eth0.3", "eth0.4", "eth0.5", "eth0.1"],
  "turris-omnia": ["eth0.1", "eth0.2", "eth0.3", "eth0.3", "eth0.5"],
  "ubnt-erx": ["eth0.1", "eth0.2", "eth0.3", "eth0.4", "eth0.5"],
  "ubnt-unifiac-lite": ["eth0"],
  "zyxel_nbg6817": ["eth1.1", "eth1.2", "eth1.3", "eth1.4", "eth0.5"],
  "tplink_archer-a6-v3": ["wan","lan1","lan2","lan3","lan4"]
}
